{
    "global_exclude": [
        "-*************",
        "--*************"
    ],
    "users_include": {
        "1": [
            "--*************",
            "--*************",
            "--*************",
            "--*************",
            "--*************",
            "--*************",
            "--*************",
            "--*************",
            "--*************",
            "--*************",
            "--*************",
            "--*************",
            "--*************",
            "--*************",
            "--*************",
            "--*************",
            "--*************",
            "--*************",
            "--*************",
            "--*************",
            "--*************",
            "--*************",
            "--*************"
        ],
        "2": [],
        "6": [],
        "8": []
    },
    "couples": {
        "--*************": {
            "name": "MDS │ Карьерный Центр Ultimate Education",
            "tags": []
        },
        "--*************": {
            "name": "Специалист по санкционному комплаенсу 10",
            "tags": [
                "ССК 10 Б",
                "ССК 10 О и П"
            ]
        },
        "--*************": {
            "name": "Рекламное право - 8 поток",
            "tags": [
                "РП 8"
            ]
        },
        "--*************": {
            "name": "Юрист по ВЭД - 7 поток",
            "tags": []
        },
        "--*************": {
            "name": "Blockchain Lawyer - 27 поток",
            "tags": [
                "БСЛ 27"
            ]
        },
        "--*************": {
            "name": "Юрист в электронной коммерции - 12 поток",
            "tags": []
        },
        "--*************": {
            "name": "Moscow Digital School",
            "tags": []
        },
        "--*************": {
            "name": "Юрист в IT 2.0 - 4 поток",
            "tags": [
                "ИТ 2.0. БОП 4 поток"
            ]
        },
        "--*************": {
            "name": "Защита персональных данных 2.0 - 2 поток",
            "tags": [
                "ЗПД 2.0 БОП 2 поток",
                "ЗПД 2.0 О И П 2 поток"
            ]
        },
        "--*************": {
            "name": "Защита персональных данных 2.0 - 1 поток",
            "tags": [
                "ЗПД 2.0 О И П 1 поток",
                "ЗПД 2.0 БОП 1 поток"
            ]
        },
        "--*************": {
            "name": "МПдБ 2.0 - 1 поток",
            "tags": [
                "МПдБ 2.0 БОП 1 поток",
                "МПдБ 2.0 О и П 1 поток"
            ]
        },
        "--*************": {
            "name": "Юрист по ВЭД - 8 поток",
            "tags": []
        },
        "--*************": {
            "name": "Специалист по санкционному комплаенсу - 9 поток",
            "tags": [
                "ССК 9 Б",
                "ССК 9 О и П"
            ]
        },
        "--*************": {
            "name": "Юрист в электронной коммерции - 11 поток",
            "tags": []
        },
        "--*************": {
            "name": "Юрист в M&A 2.0 - 2 поток",
            "tags": [
                "МА 2.0 БОП 2 поток"
            ]
        },
        "--*************": {
            "name": "Юрист по ВЭД. 6 поток",
            "tags": []
        },
        "--*************": {
            "name": "Blockchain Lawyer - 28 поток",
            "tags": [
                "БСЛ 28"
            ]
        },
        "--*************": {
            "name": "Юрист в M&A 2.0 1 поток",
            "tags": [
                "МА 2.0 БОП 1 поток"
            ]
        },
        "--*************": {
            "name": "Юрист в IT 2.0 - 3 поток",
            "tags": [
                "ИТ 2.0. БОП 3 поток"
            ]
        },
        "--*************": {
            "name": "Юрист в IT 2.0 - 2 поток",
            "tags": [
                "ИТ 2.0. БОП 2 поток"
            ]
        },
        "--*************": {
            "name": "Юрист в IT 2.0 - 6 поток",
            "tags": [
                "ИТ 2.0. БОП 6 поток"
            ]
        },
        "--*************": {
            "name": "Юрист в IT 2.0 - 1 поток",
            "tags": [
                "ИТ 2.0. БОП 1 поток"
            ]
        },
        "--*************": {
            "name": "Специалист по санкционному комплаенсу 11",
            "tags": [
                "ССК 11 Б",
                "ССК 11 О и П"
            ]
        },
        "--*************": {
            "name": "МПдБ 2.0 - 2 поток",
            "tags": [
                "МПдБ 2.0 БОП 2 поток",
                "МПдБ 2.0 О и П 2 поток"
            ]
        },
        "--*************": {
            "name": "Юрист в M&A 2.0 - 3 Поток",
            "tags": [
                "МА 2.0 БОП 3 поток"
            ]
        },
        "--*************": {
            "name": "Юрист в IT 2.0 - 5 поток",
            "tags": [
                "ИТ 2.0. БОП 5 поток"
            ]
        },
        "--*************": {
            "name": "Юрист в M&A - 11 поток",
            "tags": []
        },
        "--*************": {
            "name": "Юрист в IT 2.0 - 6 поток",
            "tags": [
                "ИТ 2.0. БОП 6 поток",
                "ИТ 2.0. О и П 6 поток"
            ]
        },
        "--*************": {
            "name": "Рекламное право - 8 поток",
            "tags": [
                "РП 8"
            ]
        },
        "--*************": {
            "name": "Специалист по санкционному комплаенсу - 8 поток",
            "tags": [
                "ССК 8 (Б)",
                "ССК 8 (О и П)"
            ]
        },
        "--*************": {
            "name": "Специалист по санкционному комплаенсу - 7 поток",
            "tags": [
                "ССК 7 (Б)",
                "ССК 7 (О и П)"
            ]
        },
        "--*************": {
            "name": "Международное право для бизнеса - 6 поток",
            "tags": []
        },
        "--*************": {
            "name": "Международное право для бизнеса - 5 поток",
            "tags": [
                "МПБ 5"
            ]
        },
        "--*************": {
            "name": "Защита персональных данных - 7 поток",
            "tags": [
                "ЗПД 7"
            ]
        },
        "--*************": {
            "name": "Юрист по ВЭД - 5 поток",
            "tags": []
        },
        "--*************": {
            "name": "Юрист в электронной коммерции - 10 поток",
            "tags": []
        },
        "--*************": {
            "name": "Юрист в сфере IT - 17 поток",
            "tags": []
        },
        "--*************": {
            "name": "Юрист в сфере IT - 16 поток",
            "tags": []
        },
        "--*************": {
            "name": "Blockchain Lawyer - 26 поток",
            "tags": [
                "БСЛ 26"
            ]
        },
        "--*************": {
            "name": "Юрист в M&A 2.0 - 4 поток",
            "tags": []
        },
        "--*************": {
            "name": "Защита персональных данных - 8 поток",
            "tags": [
                "ЗПД 8"
            ]
        },
        "--*************": {
            "name": "МПдБ 2.0 - 3 поток",
            "tags": [
                "МПдБ 2.0 БОП 3 поток",
                "МПдБ 2.0 О и П 3 поток"
            ]
        },
        "--*************": {
            "name": "Юрист в электронной коммерции - 13 поток",
            "tags": []
        },
        "--*************": {
            "name": "Защита персональных данных 2.0 - 3 поток",
            "tags": [
                "ЗПД 2.0 БОП 2 поток",
                "ЗПД 2.0 О И П 2 поток"
            ]
        },
        "--*************": {
            "name": "Юрист в IT 2.0 - 7 поток",
            "tags": [
                "ИТ 2.0. О и П 7 поток",
                "ИТ 2.0. О и П 7 и 8 поток"
            ]
        },
        "--*************": {
            "name": "Юрист в M&A 2.0 - 5 поток",
            "tags": []
        },
        "--*************": {
            "name": "Юрист по ВЭД - 9 поток",
            "tags": []
        },
        "--*************": {
            "name": "Blockchain Lawyer - 29 поток",
            "tags": []
        },
        "--*************": {
            "name": "Юрист в IT 2.0 - 8 поток",
            "tags": [
                "ИТ 2.0. О и П 8 поток",
                "ИТ 2.0. О и П 7 и 8 поток"
            ]
        },
        "--*************": {
            "name": "Blockchain Lawyer - 30 поток",
            "tags": []
        },
        "--*************": {
            "name": "Юрист в электронной коммерции - 14 поток",
            "tags": []
        },
        "--*************": {
            "name": "Защита персональных данных 2.0 - 5 поток",
            "tags": []
        },
        "--*************": {
            "name": "Специалист по санкционному комплаенсу 12",
            "tags": []
        },
        "--*************": {
            "name": "Юрист по ВЭД - 10 поток",
            "tags": []
        },
        "--*************": {
            "name": "Юрист в IT 2.0 - 9 поток",
            "tags": [
                "ИТ 2.0. О и П 9 поток"
            ]
        },
        "--*************": {
            "name": "Юрист в M&A 2.0 - 6 поток",
            "tags": []
        },
        "--*************": {
            "name": "МПдБ 2.0 - 4 поток",
            "tags": []
        }
    }
}